pytsdb.py
setup.py
pytsdb.egg-info/PKG-INFO
pytsdb.egg-info/SOURCES.txt
pytsdb.egg-info/dependency_links.txt
pytsdb.egg-info/requires.txt
pytsdb.egg-info/top_level.txt