Metadata-Version: 1.0
Name: pytsdb
Version: 0.2.1
Summary: Featureless Python adapter for OpenTSDB
Home-page: https://github.com/whoopinc/pytsdb
Author: Nikhil Benesch
Author-email: nikhil.benesch@gmail.com
License: UNKNOWN
Platform: UNKNOWN
